youtube_history_analysis/__init__.py
youtube_history_analysis/__main__.py
youtube_history_analysis/py.typed
youtube_history_analysis-1.0.2.dist-info/WHEEL
youtube_history_analysis-1.0.2.dist-info/METADATA
youtube_history_analysis-1.0.2.dist-info/RECORD
