Metadata-Version: 2.1
Name: youtube-history-analysis
Version: 1.0.2
Summary: See how your YouTube interests evolved over time
Home-page: https://armanckeser.github.io/youtube-history-analysis
License: MIT
Author: Armanc Keser
Author-email: armanckeser@hotmail.com
Requires-Python: >=3.9.0,<3.12
Classifier: Development Status :: 4 - Beta
Classifier: Intended Audience :: Developers
Classifier: License :: OSI Approved :: MIT License
Classifier: Operating System :: OS Independent
Classifier: Programming Language :: Python
Classifier: Programming Language :: Python :: 3
Classifier: Programming Language :: Python :: 3.9
Classifier: Programming Language :: Python :: 3.10
Classifier: Programming Language :: Python :: 3.11
Classifier: Programming Language :: Python :: 3
Classifier: Programming Language :: Python :: 3.9
Classifier: Topic :: Software Development :: Libraries :: Python Modules
Classifier: Typing :: Typed
Requires-Dist: google-api-python-client (>=2.68.0,<3.0.0)
Requires-Dist: matplotlib (>=3.6.2,<4.0.0)
Requires-Dist: numpy (>=1.23.5,<2.0.0)
Requires-Dist: pandas (>=1.5.2,<2.0.0)
Requires-Dist: typer[all] (>=0.7.0,<0.8.0)
Project-URL: Documentation, https://armanckeser.github.io/youtube-history-analysis
Project-URL: Repository, https://github.com/armanckeser/youtube-history-analysis
